[{"seconds":1.2298264,"direction":1},{"seconds":1.5497271,"direction":2},{"seconds":1.9898355,"direction":1},{"seconds":2.381723,"direction":2},{"seconds":2.9497743,"direction":1},{"seconds":3.4618486,"direction":2},{"seconds":3.9339902,"direction":1},{"seconds":4.4778462,"direction":2},{"seconds":4.9417516,"direction":1},{"seconds":5.4140202,"direction":2},{"seconds":5.8779525,"direction":1},{"seconds":6.8619332,"direction":1},{"seconds":7.3179299,"direction":2},{"seconds":7.9418123,"direction":1},{"seconds":8.3258727,"direction":2},{"seconds":8.74188,"direction":1},{"seconds":9.741788,"direction":2},{"seconds":10.6616957,"direction":1},{"seconds":11.1979711,"direction":2},{"seconds":11.6698765,"direction":1},{"seconds":12.1417494,"direction":2},{"seconds":12.8216603,"direction":1},{"seconds":13.6699916,"direction":2},{"seconds":14.7979561,"direction":1},{"seconds":16.3661459,"direction":2},{"seconds":18.2778246,"direction":1},{"seconds":18.5901027,"direction":2},{"seconds":20.3578657,"direction":1},{"seconds":21.4382793,"direction":2},{"seconds":22.3258461,"direction":1},{"seconds":23.197984,"direction":2},{"seconds":24.325879,"direction":1},{"seconds":24.7740016,"direction":2},{"seconds":25.2936686,"direction":1},{"seconds":26.2544467,"direction":2},{"seconds":27.2058586,"direction":1},{"seconds":28.1179937,"direction":2},{"seconds":29.0538195,"direction":1},{"seconds":30.0538439,"direction":2},{"seconds":31.4537483,"direction":1},{"seconds":32.0139887,"direction":2},{"seconds":32.9103796,"direction":1},{"seconds":34.005729,"direction":2},{"seconds":35.869995,"direction":1},{"seconds":36.8140702,"direction":2},{"seconds":37.8377439,"direction":1},{"seconds":38.7418128,"direction":2},{"seconds":39.5659532,"direction":1},{"seconds":40.0537996,"direction":2},{"seconds":40.6299492,"direction":1},{"seconds":41.7017192,"direction":2},{"seconds":42.5899261,"direction":1},{"seconds":43.7419779,"direction":2},{"seconds":44.5658298,"direction":1},{"seconds":45.1739072,"direction":2},{"seconds":45.6216653,"direction":1},{"seconds":46.6378584,"direction":2},{"seconds":47.4618401,"direction":2},{"seconds":47.9659825,"direction":1},{"seconds":48.5177391,"direction":2},{"seconds":49.4138403,"direction":1},{"seconds":50.301813,"direction":2},{"seconds":51.2938036,"direction":1},{"seconds":51.7897806,"direction":2},{"seconds":52.3117078,"direction":1},{"seconds":53.2057686,"direction":2},{"seconds":54.1736686,"direction":1},{"seconds":55.1897879,"direction":2},{"seconds":55.6617714,"direction":1},{"seconds":56.1977286,"direction":2},{"seconds":57.1656241,"direction":1},{"seconds":58.0377901,"direction":2},{"seconds":58.9898028,"direction":1},{"seconds":59.5256439,"direction":2},{"seconds":60.0136145,"direction":1},{"seconds":60.901638,"direction":2},{"seconds":61.9098976,"direction":1},{"seconds":62.9258904,"direction":2},{"seconds":63.9019432,"direction":1},{"seconds":64.7977875,"direction":2},{"seconds":65.7977625,"direction":1},{"seconds":66.2217539,"direction":2},{"seconds":66.8699955,"direction":1},{"seconds":67.3658587,"direction":2},{"seconds":67.8059994,"direction":1},{"seconds":68.693799,"direction":2},{"seconds":69.6139168,"direction":2},{"seconds":69.9258617,"direction":1},{"seconds":70.6619046,"direction":2},{"seconds":71.6218434,"direction":1},{"seconds":72.541996,"direction":2},{"seconds":73.5098986,"direction":2},{"seconds":73.8538681,"direction":1},{"seconds":74.5978617,"direction":2},{"seconds":75.5178482,"direction":1},{"seconds":76.5337318,"direction":2},{"seconds":77.4857833,"direction":1},{"seconds":78.5099851,"direction":2},{"seconds":79.4377445,"direction":1},{"seconds":80.5660205,"direction":2},{"seconds":84.0862764,"direction":1},{"seconds":85.2377354,"direction":2},{"seconds":86.2616685,"direction":1},{"seconds":87.3097159,"direction":2},{"seconds":88.0698209,"direction":1},{"seconds":89.1100354,"direction":2},{"seconds":89.9978825,"direction":1},{"seconds":90.877593,"direction":2},{"seconds":92.0380281,"direction":1},{"seconds":92.8857391,"direction":2},{"seconds":93.9820017,"direction":1},{"seconds":94.9099542,"direction":2},{"seconds":95.9018302,"direction":2},{"seconds":96.4056975,"direction":1},{"seconds":96.9496489,"direction":2},{"seconds":97.7978128,"direction":1},{"seconds":100.6375885,"direction":2},{"seconds":100.8536949,"direction":1},{"seconds":101.6938748,"direction":1},{"seconds":102.6617924,"direction":2},{"seconds":103.6058986,"direction":1},{"seconds":104.517865,"direction":2},{"seconds":105.4777398,"direction":1},{"seconds":106.4537545,"direction":2},{"seconds":107.4856888,"direction":1},{"seconds":107.5735073,"direction":1},{"seconds":108.3895941,"direction":2},{"seconds":109.3738866,"direction":1},{"seconds":110.3416748,"direction":2},{"seconds":111.3016338,"direction":1},{"seconds":112.2938473,"direction":2},{"seconds":113.2775681,"direction":1},{"seconds":114.221727,"direction":2},{"seconds":115.1575745,"direction":1},{"seconds":115.6858778,"direction":2},{"seconds":116.1736796,"direction":1},{"seconds":116.5816699,"direction":2},{"seconds":117.1737528,"direction":1},{"seconds":117.4217069,"direction":2},{"seconds":117.6216868,"direction":1},{"seconds":118.0855641,"direction":2},{"seconds":119.0936782,"direction":1},{"seconds":120.0056729,"direction":2},{"seconds":121.0457434,"direction":1},{"seconds":121.2858816,"direction":2},{"seconds":121.4856796,"direction":1},{"seconds":121.9655844,"direction":2},{"seconds":122.9416501,"direction":1},{"seconds":123.8695382,"direction":2},{"seconds":124.941785,"direction":1},{"seconds":125.1658388,"direction":2},{"seconds":125.4295871,"direction":1},{"seconds":125.8777158,"direction":2},{"seconds":126.8138893,"direction":1},{"seconds":127.7418575,"direction":2},{"seconds":128.7657124,"direction":1},{"seconds":129.6937308,"direction":2},{"seconds":130.6937493,"direction":1},{"seconds":131.5575515,"direction":2},{"seconds":132.0776551,"direction":1},{"seconds":132.6301166,"direction":2},{"seconds":133.5418911,"direction":1},{"seconds":134.0536027,"direction":2},{"seconds":134.5336477,"direction":1},{"seconds":135.5656676,"direction":2},{"seconds":136.0538986,"direction":1},{"seconds":136.5096582,"direction":2},{"seconds":137.4300867,"direction":1},{"seconds":138.4056698,"direction":2},{"seconds":138.9656918,"direction":1},{"seconds":139.3976774,"direction":2},{"seconds":140.3737673,"direction":1},{"seconds":141.2458912,"direction":2},{"seconds":142.2457134,"direction":1},{"seconds":142.8458535,"direction":2},{"seconds":143.3259099,"direction":1},{"seconds":144.2215591,"direction":2},{"seconds":145.2297722,"direction":1},{"seconds":146.1896245,"direction":2},{"seconds":146.6538833,"direction":1},{"seconds":147.0707019,"direction":2},{"seconds":148.1306912,"direction":1},{"seconds":149.0377015,"direction":2},{"seconds":149.5256763,"direction":1},{"seconds":150.0775062,"direction":2},{"seconds":151.0377394,"direction":1},{"seconds":151.9576862,"direction":2},{"seconds":152.9176002,"direction":1},{"seconds":153.3575602,"direction":2},{"seconds":153.8695376,"direction":1},{"seconds":154.9178766,"direction":2},{"seconds":155.893893,"direction":1},{"seconds":156.8056728,"direction":2},{"seconds":157.7896046,"direction":1},{"seconds":158.2777318,"direction":2},{"seconds":158.7415462,"direction":1},{"seconds":159.6937971,"direction":2},{"seconds":160.6778025,"direction":1},{"seconds":161.5901988,"direction":2},{"seconds":162.117577,"direction":1},{"seconds":162.6056014,"direction":2},{"seconds":163.6136578,"direction":1},{"seconds":164.5179347,"direction":2},{"seconds":165.4857308,"direction":1},{"seconds":166.4456487,"direction":2},{"seconds":167.5336842,"direction":1},{"seconds":168.3978074,"direction":2},{"seconds":169.461494,"direction":1},{"seconds":169.9098888,"direction":2},{"seconds":170.3815572,"direction":1},{"seconds":171.2777745,"direction":2},{"seconds":172.2776307,"direction":1},{"seconds":173.2057132,"direction":2},{"seconds":173.7736684,"direction":1},{"seconds":174.2456662,"direction":2},{"seconds":175.173611,"direction":1},{"seconds":176.1575747,"direction":2},{"seconds":177.0776504,"direction":1},{"seconds":177.6776622,"direction":2},{"seconds":178.1095974,"direction":1},{"seconds":179.0776475,"direction":2},{"seconds":179.5899428,"direction":1},{"seconds":180.0536833,"direction":2},{"seconds":180.9095142,"direction":1},{"seconds":181.9095708,"direction":2},{"seconds":182.8297921,"direction":1},{"seconds":183.4695007,"direction":2},{"seconds":183.9575804,"direction":1},{"seconds":184.8455418,"direction":2},{"seconds":185.8377774,"direction":1},{"seconds":186.7255934,"direction":2},{"seconds":187.2537953,"direction":1},{"seconds":187.7417789,"direction":2},{"seconds":188.7337411,"direction":1},{"seconds":189.7577581,"direction":2},{"seconds":190.6617315,"direction":1},{"seconds":191.1176921,"direction":2},{"seconds":191.6296078,"direction":1},{"seconds":192.5258329,"direction":2},{"seconds":193.5817201,"direction":1},{"seconds":194.5658481,"direction":2},{"seconds":195.061888,"direction":1},{"seconds":195.4775498,"direction":2},{"seconds":196.5095794,"direction":1},{"seconds":197.3738355,"direction":2},{"seconds":198.197531,"direction":1},{"seconds":198.733721,"direction":2},{"seconds":199.2936445,"direction":1},{"seconds":200.1417224,"direction":2},{"seconds":201.2857263,"direction":1},{"seconds":202.2456707,"direction":2},{"seconds":202.797652,"direction":1},{"seconds":203.2628901,"direction":2},{"seconds":204.2055582,"direction":1},{"seconds":205.1175875,"direction":2},{"seconds":206.1498461,"direction":1},{"seconds":207.1095667,"direction":2},{"seconds":208.0294926,"direction":1},{"seconds":208.565865,"direction":2},{"seconds":209.0455313,"direction":1},{"seconds":209.8536348,"direction":2},{"seconds":210.7175121,"direction":1},{"seconds":211.2375833,"direction":2},{"seconds":211.5499135,"direction":1},{"seconds":211.9975949,"direction":2}]